ntsh/__init__.py
ntsh/main.py
ntsh/protocols.py
ntsh/katcp/__init__.py
ntsh/katcp/lexer.py
ntsh-1.1.3.dist-info/COPYING
ntsh-1.1.3.dist-info/METADATA
ntsh-1.1.3.dist-info/WHEEL
ntsh-1.1.3.dist-info/entry_points.txt
ntsh-1.1.3.dist-info/top_level.txt
ntsh-1.1.3.dist-info/RECORD
