Metadata-Version: 2.1
Name: ntsh
Version: 1.1.3
Summary: Interactive tool for line-based protocols
Author: Bruce Merry
License: GPLv3+
Classifier: Development Status :: 5 - Production/Stable
Classifier: Environment :: Console
Classifier: Intended Audience :: Developers
Classifier: License :: OSI Approved :: GNU General Public License v3 or later (GPLv3+)
Classifier: Operating System :: OS Independent
Classifier: Programming Language :: Python :: 3 :: Only
Classifier: Topic :: System :: Networking
Requires-Python: >=3.8
License-File: COPYING
Requires-Dist: prompt-toolkit <4,>=3
Requires-Dist: pygments
Requires-Dist: appdirs
